Workbook

Sheet Cronograma
A1: Cronograma de Desenvolvimento - Aplicacao de Alugueis
A3: ID | B3: Fase | C3: Entrega principal | D3: Inicio | E3: Fim | F3: Semanas | G3: Prioridade | H3: Responsavel | I3: Status | J3: Dependencia | K3: Observacoes | M3: Linha do tempo semanal | N3: S1 | O3: S2 | P3: S3 | Q3: S4 | R3: S5 | S3: S6 | T3: S7 | U3: S8
A4: 1 | B4: Descoberta e modelagem | C4: Validar regras de negocio, modelo de recebimento e escopo do MVP | D4: 46201 | E4: 46207 | F4: =ROUNDUP((E4-D4+1)/7,0) -> 1 | G4: Alta | H4: Produto / Negocio | I4: Concluido | J4: Nenhuma | K4: Requisitos originais documentados (outputs/instrucoes-aplicacao-alugueis.md); escopo revisado apos decisao pela stack Cloudflare. | N4: 46201 | O4: 46208 | P4: 46215 | Q4: 46222 | R4: 46229 | S4: 46236 | T4: 46243 | U4: 46250
A5: 2 | B5: Arquitetura e base tecnica | C5: Criar monolito, banco, autenticacao base e ambiente de deploy | D5: 46208 | E5: 46208 | F5: =ROUNDUP((E5-D5+1)/7,0) -> 1 | G5: Alta | H5: Desenvolvimento | I5: Concluido | J5: Fase 1 | K5: Stack real: vinext + Cloudflare Workers + D1 + R2 (diferente da proposta original Laravel/Django + PostgreSQL). Deploy em property-manager.lucasfbraun.workers.dev. | M5: Descoberta e modelagem | N5: =IF(AND(N$4>=$D5,N$4<=$E5),"x","") | O5: =IF(AND(O$4>=$D5,O$4<=$E5),"x","") -> x | P5: =IF(AND(P$4>=$D5,P$4<=$E5),"x","") | Q5: =IF(AND(Q$4>=$D5,Q$4<=$E5),"x","") | R5: =IF(AND(R$4>=$D5,R$4<=$E5),"x","") | S5: =IF(AND(S$4>=$D5,S$4<=$E5),"x","") | T5: =IF(AND(T$4>=$D5,T$4<=$E5),"x","") | U5: =IF(AND(U$4>=$D5,U$4<=$E5),"x","")
A6: 3 | B6: Usuarios e permissoes | C6: Perfis de administrador, recebedor e inquilino | D6: 46208 | E6: 46208 | F6: =ROUNDUP((E6-D6+1)/7,0) -> 1 | G6: Alta | H6: Desenvolvimento | I6: Concluido | J6: Fase 2 | K6: Autenticacao por sessao (cookie) com hash PBKDF2-SHA256 e 3 papeis implementada. | M6: Arquitetura e base tecnica | N6: =IF(AND(N$4>=$D6,N$4<=$E6),"x","") | O6: =IF(AND(O$4>=$D6,O$4<=$E6),"x","") -> x | P6: =IF(AND(P$4>=$D6,P$4<=$E6),"x","") | Q6: =IF(AND(Q$4>=$D6,Q$4<=$E6),"x","") | R6: =IF(AND(R$4>=$D6,R$4<=$E6),"x","") | S6: =IF(AND(S$4>=$D6,S$4<=$E6),"x","") | T6: =IF(AND(T$4>=$D6,T$4<=$E6),"x","") | U6: =IF(AND(U$4>=$D6,U$4<=$E6),"x","")
A7: 4 | B7: Cadastros principais | C7: Imoveis, inquilinos, recebedores e dados auxiliares | D7: 46208 | E7: 46208 | F7: =ROUNDUP((E7-D7+1)/7,0) -> 1 | G7: Alta | H7: Desenvolvimento | I7: Concluido | J7: Fase 3 | K7: CRUD completo (criar, editar, excluir com guarda de vinculos) auditado em 05/07/2026. | M7: Usuarios e permissoes | N7: =IF(AND(N$4>=$D7,N$4<=$E7),"x","") | O7: =IF(AND(O$4>=$D7,O$4<=$E7),"x","") -> x | P7: =IF(AND(P$4>=$D7,P$4<=$E7),"x","") | Q7: =IF(AND(Q$4>=$D7,Q$4<=$E7),"x","") | R7: =IF(AND(R$4>=$D7,R$4<=$E7),"x","") | S7: =IF(AND(S$4>=$D7,S$4<=$E7),"x","") | T7: =IF(AND(T$4>=$D7,T$4<=$E7),"x","") | U7: =IF(AND(U$4>=$D7,U$4<=$E7),"x","")
A8: 5 | B8: Seguranca de API e edicao completa nos CRUDs | C8: Proteger rotas de API por papel e habilitar edicao total dos cadastros | D8: 46208 | E8: 46208 | F8: =ROUNDUP((E8-D8+1)/7,0) -> 1 | G8: Alta | H8: Desenvolvimento | I8: Concluido | J8: Fase 4 | K8: Escopo adicional identificado e entregue: todas as rotas de API exigem admin autenticado; PATCH adicionado a todas as entidades. | M8: Cadastros principais | N8: =IF(AND(N$4>=$D8,N$4<=$E8),"x","") | O8: =IF(AND(O$4>=$D8,O$4<=$E8),"x","") -> x | P8: =IF(AND(P$4>=$D8,P$4<=$E8),"x","") | Q8: =IF(AND(Q$4>=$D8,Q$4<=$E8),"x","") | R8: =IF(AND(R$4>=$D8,R$4<=$E8),"x","") | S8: =IF(AND(S$4>=$D8,S$4<=$E8),"x","") | T8: =IF(AND(T$4>=$D8,T$4<=$E8),"x","") | U8: =IF(AND(U$4>=$D8,U$4<=$E8),"x","")
A9: 6 | B9: Contratos | C9: Cadastro de contratos, vencimento, recebedor, valores e regras | D9: 46208 | E9: 46208 | F9: =ROUNDUP((E9-D9+1)/7,0) -> 1 | G9: Alta | H9: Desenvolvimento | I9: Concluido | J9: Fase 5 | K9: Cadastro completo de contratos com calculo de multa, juros e carencia. | M9: Seguranca de API e edicao completa nos CRUDs | N9: =IF(AND(N$4>=$D9,N$4<=$E9),"x","") | O9: =IF(AND(O$4>=$D9,O$4<=$E9),"x","") -> x | P9: =IF(AND(P$4>=$D9,P$4<=$E9),"x","") | Q9: =IF(AND(Q$4>=$D9,Q$4<=$E9),"x","") | R9: =IF(AND(R$4>=$D9,R$4<=$E9),"x","") | S9: =IF(AND(S$4>=$D9,S$4<=$E9),"x","") | T9: =IF(AND(T$4>=$D9,T$4<=$E9),"x","") | U9: =IF(AND(U$4>=$D9,U$4<=$E9),"x","")
A10: 7 | B10: Templates de contrato e assinatura eletronica | C10: Templates nomeados, geracao por inquilino, download em PDF, upload assinado e fila de aprovacao | D10: 46208 | E10: 46208 | F10: =ROUNDUP((E10-D10+1)/7,0) -> 1 | G10: Alta | H10: Desenvolvimento | I10: Concluido | J10: Fase 6 | K10: Fora do escopo do MVP original (listado como 'fora do MVP inicial' no documento de requisitos); adicionado por solicitacao explicita. Emails via Resend na aprovacao/rejeicao. | M10: Contratos | N10: =IF(AND(N$4>=$D10,N$4<=$E10),"x","") | O10: =IF(AND(O$4>=$D10,O$4<=$E10),"x","") -> x | P10: =IF(AND(P$4>=$D10,P$4<=$E10),"x","") | Q10: =IF(AND(Q$4>=$D10,Q$4<=$E10),"x","") | R10: =IF(AND(R$4>=$D10,R$4<=$E10),"x","") | S10: =IF(AND(S$4>=$D10,S$4<=$E10),"x","") | T10: =IF(AND(T$4>=$D10,T$4<=$E10),"x","") | U10: =IF(AND(U$4>=$D10,U$4<=$E10),"x","")
A11: 8 | B11: Armazenamento de documentos assinados (R2) | C11: Migrar PDF assinado de blob no D1 para o Cloudflare R2 | D11: 46208 | E11: 46208 | F11: =ROUNDUP((E11-D11+1)/7,0) -> 1 | G11: Media | H11: Desenvolvimento | I11: Concluido | J11: Fase 7 | K11: Custo/escala mais adequados ao volume esperado (poucos contratos); limite de arquivo elevado para 15MB. | M11: Templates de contrato e assinatura eletronica | N11: =IF(AND(N$4>=$D11,N$4<=$E11),"x","") | O11: =IF(AND(O$4>=$D11,O$4<=$E11),"x","") -> x | P11: =IF(AND(P$4>=$D11,P$4<=$E11),"x","") | Q11: =IF(AND(Q$4>=$D11,Q$4<=$E11),"x","") | R11: =IF(AND(R$4>=$D11,R$4<=$E11),"x","") | S11: =IF(AND(S$4>=$D11,S$4<=$E11),"x","") | T11: =IF(AND(T$4>=$D11,T$4<=$E11),"x","") | U11: =IF(AND(U$4>=$D11,U$4<=$E11),"x","")
A12: 9 | B12: Cobrancas e regras financeiras | C12: Calculo de multa, juros, descontos e historico de cobrancas | D12: 46208 | E12: 46208 | F12: =ROUNDUP((E12-D12+1)/7,0) -> 1 | G12: Alta | H12: Desenvolvimento | I12: Concluido | J12: Fase 6 | K12: Calculo de valor atualizado (multa + juros + carencia) implementado e lido do D1. | M12: Armazenamento de documentos assinados (R2) | N12: =IF(AND(N$4>=$D12,N$4<=$E12),"x","") | O12: =IF(AND(O$4>=$D12,O$4<=$E12),"x","") -> x | P12: =IF(AND(P$4>=$D12,P$4<=$E12),"x","") | Q12: =IF(AND(Q$4>=$D12,Q$4<=$E12),"x","") | R12: =IF(AND(R$4>=$D12,R$4<=$E12),"x","") | S12: =IF(AND(S$4>=$D12,S$4<=$E12),"x","") | T12: =IF(AND(T$4>=$D12,T$4<=$E12),"x","") | U12: =IF(AND(U$4>=$D12,U$4<=$E12),"x","")
A13: 10 | B13: Mercado Pago Pix | C13: Cada recebedor conecta a propria conta via OAuth e gera cobranca Pix | D13: 46208 | E13: 46208 | F13: =ROUNDUP((E13-D13+1)/7,0) -> 1 | G13: Alta | H13: Desenvolvimento / Integracoes | I13: Concluido | J13: Fase 9 | K13: Modelo marketplace/split por recebedor. Sandbox do Mercado Pago se mostrou instavel para esse modelo (varios erros: client_id/secret, contas de teste, "Invalid users involved"); validado com um pagamento Pix real de R$1 em producao (ver Fase 20). Recomenda-se mais alguns testes reais de baixo valor antes do uso pleno (ver Riscos). | M13: Cobrancas e regras financeiras | N13: =IF(AND(N$4>=$D13,N$4<=$E13),"x","") | O13: =IF(AND(O$4>=$D13,O$4<=$E13),"x","") -> x | P13: =IF(AND(P$4>=$D13,P$4<=$E13),"x","") | Q13: =IF(AND(Q$4>=$D13,Q$4<=$E13),"x","") | R13: =IF(AND(R$4>=$D13,R$4<=$E13),"x","") | S13: =IF(AND(S$4>=$D13,S$4<=$E13),"x","") | T13: =IF(AND(T$4>=$D13,T$4<=$E13),"x","") | U13: =IF(AND(U$4>=$D13,U$4<=$E13),"x","")
A14: 11 | B14: Webhooks e conciliacao | C14: Confirmacao automatica de pagamento, idempotencia e validacao de assinatura | D14: 46208 | E14: 46208 | F14: =ROUNDUP((E14-D14+1)/7,0) -> 1 | G14: Alta | H14: Desenvolvimento / Integracoes | I14: Concluido | J14: Fase 10 | K14: Validacao HMAC do webhook e checagem de external_id antes de gravar pagamento. Adicionado tambem um fallback manual: botao admin "Verificar pagamento" que reconcilia a cobranca direto na API da MP quando o webhook nao chega (ver Fase 20). | M14: Mercado Pago Pix | N14: =IF(AND(N$4>=$D14,N$4<=$E14),"x","") | O14: =IF(AND(O$4>=$D14,O$4<=$E14),"x","") -> x | P14: =IF(AND(P$4>=$D14,P$4<=$E14),"x","") | Q14: =IF(AND(Q$4>=$D14,Q$4<=$E14),"x","") | R14: =IF(AND(R$4>=$D14,R$4<=$E14),"x","") | S14: =IF(AND(S$4>=$D14,S$4<=$E14),"x","") | T14: =IF(AND(T$4>=$D14,T$4<=$E14),"x","") | U14: =IF(AND(U$4>=$D14,U$4<=$E14),"x","")
A15: 12 | B15: Geracao de cobranca mensal (manual e automatica) | C15: Botao de geracao manual e Cron Trigger diario para geracao automatica | D15: 46208 | E15: 46208 | F15: =ROUNDUP((E15-D15+1)/7,0) -> 1 | G15: Alta | H15: Desenvolvimento | I15: Concluido | J15: Fase 9 | K15: Janela de 5 dias antes do vencimento (com reprocessamento de ate 3 dias em atraso); checagem de duplicidade por contrato e mes. | M15: Webhooks e conciliacao | N15: =IF(AND(N$4>=$D15,N$4<=$E15),"x","") | O15: =IF(AND(O$4>=$D15,O$4<=$E15),"x","") -> x | P15: =IF(AND(P$4>=$D15,P$4<=$E15),"x","") | Q15: =IF(AND(Q$4>=$D15,Q$4<=$E15),"x","") | R15: =IF(AND(R$4>=$D15,R$4<=$E15),"x","") | S15: =IF(AND(S$4>=$D15,S$4<=$E15),"x","") | T15: =IF(AND(T$4>=$D15,T$4<=$E15),"x","") | U15: =IF(AND(U$4>=$D15,U$4<=$E15),"x","")
A16: 13 | B16: Portal do inquilino | C16: Consulta de contrato, cobrancas, historico, comprovantes e pagamento Pix | D16: 46208 | E16: 46208 | F16: =ROUNDUP((E16-D16+1)/7,0) -> 1 | G16: Alta | H16: Desenvolvimento / UX | I16: Concluido | J16: Fases 9 a 12 | K16: Portal conectado aos dados reais do D1, com botao de Pix e status/link do contrato. | M16: Geracao de cobranca mensal (manual e automatica) | N16: =IF(AND(N$4>=$D16,N$4<=$E16),"x","") | O16: =IF(AND(O$4>=$D16,O$4<=$E16),"x","") -> x | P16: =IF(AND(P$4>=$D16,P$4<=$E16),"x","") | Q16: =IF(AND(Q$4>=$D16,Q$4<=$E16),"x","") | R16: =IF(AND(R$4>=$D16,R$4<=$E16),"x","") | S16: =IF(AND(S$4>=$D16,S$4<=$E16),"x","") | T16: =IF(AND(T$4>=$D16,T$4<=$E16),"x","") | U16: =IF(AND(U$4>=$D16,U$4<=$E16),"x","")
... A21: 18 | B21: Homologacao e lancamento | C21: Testes de ponta a ponta, LGPD, backups, monitoramento e treinamento | D21: 46230 | E21: 46243 | F21: =ROUNDUP((E21-D21+1)/7,0) -> 2 | G21: Alta | H21: Todos | I21: Nao iniciado | J21: Fases 1 a 17 | K21: Inclui teste real do fluxo Pix/Mercado Pago em sandbox e teste de ponta a ponta da aplicacao publicada. | M21: Autoatendimento de senha e gestao de cobrancas | N21: =IF(AND(N$4>=$D21,N$4<=$E21),"x","") | O21: =IF(AND(O$4>=$D21,O$4<=$E21),"x","") | P21: =IF(AND(P$4>=$D21,P$4<=$E21),"x","") | Q21: =IF(AND(Q$4>=$D21,Q$4<=$E21),"x","") | R21: =IF(AND(R$4>=$D21,R$4<=$E21),"x","") | S21: =IF(AND(S$4>=$D21,S$4<=$E21),"x","") -> x | T21: =IF(AND(T$4>=$D21,T$4<=$E21),"x","") -> x | U21: =IF(AND(U$4>=$D21,U$4<=$E21),"x","")
M22: Homologacao e lancamento | N22: =IF(AND(N$4>=$D22,N$4<=$E22),"x","") | O22: =IF(AND(O$4>=$D22,O$4<=$E22),"x","") | P22: =IF(AND(P$4>=$D22,P$4<=$E22),"x","") | Q22: =IF(AND(Q$4>=$D22,Q$4<=$E22),"x","") | R22: =IF(AND(R$4>=$D22,R$4<=$E22),"x","") | S22: =IF(AND(S$4>=$D22,S$4<=$E22),"x","") | T22: =IF(AND(T$4>=$D22,T$4<=$E22),"x","") | U22: =IF(AND(U$4>=$D22,U$4<=$E22),"x","")
A23: 19 | B23: Vistoria fotografica e registro de ocorrencias | C23: Fotos da vistoria embutidas no PDF do contrato gerado; inquilino registra ocorrencias com fotos e acompanha status | D23: 46214 | E23: 46214 | F23: 1 | G23: Media | H23: Desenvolvimento | I23: Concluido | J23: Fase 7 | K23: Fora do MVP original, adicionado por solicitacao explicita. Fotos da vistoria (camera ou galeria) sao embutidas diretamente no PDF gerado do contrato via pdf-lib, para resguardo em caso de disputa. Inquilino pode reportar ocorrencia (fotos + descricao) e o admin acompanha com status aberta/em analise/resolvida. | M23: Templates de contrato e assinatura eletronica | O23: x
A24: 20 | B24: Teste real do fluxo Pix e comprovante de pagamento | C24: Validacao ponta a ponta do Pix (OAuth, cobranca, webhook) e recibo de pagamento em PDF | D24: 46214 | E24: 46214 | F24: 1 | G24: Alta | H24: Desenvolvimento / Integracoes | I24: Concluido | J24: Fases 10 e 11 | K24: Corrigidos no caminho: client_secret errado (nao e o Access Token), e-mail de login do inquilino que nao sincronizava ao editar, CPF ausente no payload do Pix (obrigatorio pela MP). Webhook de producao nao estava configurado a tempo do primeiro pagamento; adicionado o botao admin "Verificar pagamento" como fallback. Recibo de pagamento em PDF (texto fixo por enquanto) liberado ao inquilino apos a cobranca ser paga. | M24: Mercado Pago Pix | O24: x
A25: 21 | B25: Rateio de agua entre imoveis | C25: Admin informa a fatura de agua do mes, seleciona os imoveis participantes e o valor e somado na cobranca de cada um | D25: 46214 | E25: 46214 | F25: 1 | G25: Media | H25: Desenvolvimento | I25: Concluido | J25: Fase 9 | K25: Opcional, adicionado por solicitacao explicita (caso de uso: predio com multiplos apartamentos do mesmo dono). Divisao igual entre os imoveis selecionados; fatura de agua (JPG/PNG/PDF) pode ser anexada; valor e somado automaticamente na cobranca do mes (na hora, se ja existir, ou quando a cobranca for gerada). | M25: Cobrancas e regras financeiras | O25: x
A26: 22 | B26: Ajustes de responsividade mobile | C26: Revisao e correcoes de UX para uso em celular | D26: 46214 | E26: 46214 | F26: 1 | G26: Media | H26: Desenvolvimento / UX | I26: Concluido | J26: Fase 13 | K26: Tabela de contratos (admin) ganhou menu de acoes compacto no celular (antes exigia rolagem horizontal por 4 botoes lado a lado). Corrigido botao de remover foto de vistoria que dependia de :hover, invisivel em telas touch. | M26: Portal do inquilino | O26: x
A27: 23 | B27: Chat de ajuda no painel admin | C27: Widget de chat flutuante no painel admin com busca por palavras-chave sobre o manual da aplicacao | D27: 46215 | E27: 46215 | F27: 1 | G27: Baixa | H27: Desenvolvimento / UX | I27: Concluido | J27: Fase 3 | K27: Adicionado por solicitacao explicita. Sem IA externa: busca por palavras-chave contra uma base de conhecimento fixa (MANUAL-ADMIN.md / help-content.ts), 100% dentro do Worker atual, nunca consulta o banco de dados (privacidade por construcao). Disponivel apenas no painel admin (dashboard, cadastros, contratos, rateios, integracoes); nao aparece no portal do inquilino nem do recebedor. | P27: x

Sheet Resumo
A1: Resumo Executivo do Projeto
A3: Indicador | B3: Valor
A4: Total de fases | B4: =COUNTA(Cronograma!A4:A27) -> 23
A5: Fases concluidas | B5: =COUNTIF(Cronograma!I4:I27,"Concluido") -> 19
A6: Fases em andamento | B6: =COUNTIF(Cronograma!I4:I27,"Em andamento") -> 1
A7: Fases nao iniciadas | B7: =COUNTIF(Cronograma!I4:I27,"Nao iniciado") -> 3
A8: Fases bloqueadas | B8: =COUNTIF(Cronograma!I4:I27,"Bloqueado") -> 0
A9: Conclusao estimada | B9: =MAX(Cronograma!E4:E27) -> 46243
A11: Decisao | B11: Por que importa | C11: Momento recomendado | D11: Status
A12: Modelo Mercado Pago | B12: Define se o pagamento vai para conta central, multiplas contas ou split | C12: Fase 10 | D12: Definido: OAuth por recebedor (marketplace/split). Sandbox instavel para esse modelo; validado com pagamento Pix real de R$1 (ver Fase 20)
A13: Stack do projeto | B13: Define produtividade, hospedagem e manutencao | C13: Fase 2 | D13: Definido: vinext + Cloudflare Workers + D1 + R2 (nao a proposta original)
A14: Provedor WhatsApp | B14: Define custo e regras de envio | C14: Fase 16 | D14: Definido (revisado 11/07/2026): Cron Trigger da Cloudflare chama o WAHA direto, sem n8n; implementacao do envio pendente
A15: Armazenamento de PDF assinado | B15: Define custo e escalabilidade do storage de contratos | C15: Fase 8 | D15: Definido: Cloudflare R2 (migrado do D1)
A16: Cartao de credito | B16: Pode aumentar escopo e prazo | C16: Pos-lancamento | D16: Pendente (fora do escopo atual, so Pix)
A18: Item | B18: Incluido? | C18: Observacao | D18: Prioridade
A19: Cadastros de imoveis, inquilinos e recebedores | B19: Sim | C19: CRUD completo entregue | D19: Alta
A20: Contratos com recebedor definido | B20: Sim | C20: Regra central da aplicacao | D20: Alta
A21: Cobrancas mensais com multa e juros | B21: Sim | C21: Geracao manual e automatica via cron entregues | D21: Alta
A22: Mercado Pago Pix | B22: Sim | C22: OAuth por recebedor; validado com pagamento Pix real (sandbox instavel para esse modelo) | D22: Alta
A23: Templates de contrato e assinatura eletronica | B23: Sim (alem do MVP) | C23: Fora do escopo original, adicionado por solicitacao | D23: Alta
... A29: Rateio de agua entre imoveis | B29: Sim (opcional) | C29: Divisao igual entre imoveis selecionados; fatura anexavel; soma automatica na cobranca | D29: Media

Sheet Riscos
A1: Riscos e Mitigacoes
A3: Impacto | B3: Risco | C3: Efeito possivel | D3: Mitigacao | E3: Status
A4: Alto | B4: Fluxo Pix/Mercado Pago nao validado ponta a ponta | C4: Falha so seria descoberta em producao, com impacto em recebimento | D4: Sandbox da MP se mostrou instavel para o modelo marketplace/OAuth (varios erros ao longo do teste). Validado em vez disso com um pagamento Pix real de R$1, confirmando OAuth, criacao de cobranca, webhook (com fallback manual "Verificar pagamento") e recibo de pagamento. | E4: Mitigado
A5: Alto | B5: Webhook duplicado ou perdido | C5: Cobranca pode ficar com status incorreto | D5: Processamento idempotente por external_id ja implementado; manter logs e reprocessamento manual | E5: Mitigado
A6: Alto | B6: Permissoes mal separadas | C6: Recebedor ou inquilino pode ver dados indevidos | D6: requireApiUser/requireUser ja aplicados a todas as rotas; manter testes de autorizacao por perfil | E6: Mitigado
A7: Medio | B7: Calculo incorreto de juros | C7: Cobranca indevida ou perda financeira | D7: Adicionar testes automatizados para multa, juros, carencia e abonos | E7: Aberto
A8: Medio | B8: Mensagens WhatsApp duplicadas | C8: Experiencia ruim para o inquilino | D8: Controlar envio por cobranca, evento e data quando a integracao Cron Trigger + WAHA (sem n8n, decisao de 11/07/2026) for implementada | E8: Aberto (fase nao iniciada)
A9: Medio | B9: Armazenamento de documentos sensiveis (contratos assinados) | C9: Risco de LGPD e seguranca | D9: PDF assinado armazenado no R2 (fora do banco); revisar politica de retencao e controle de acesso | E9: Mitigado parcialmente
A10: Medio | B10: Ausencia de teste de ponta a ponta ao vivo da aplicacao publicada | C10: Bugs de integracao podem passar despercebidos | D10: Realizar bateria de testes manuais (ou via navegador) cobrindo os fluxos criticos antes do lancamento | E10: Aberto
A11: Medio | B11: Apenas uma transacao Pix real (R$1) foi validada | C11: Casos de borda (expiracao do QR, estorno, pagamento parcial) ainda nao testados | D11: Realizar mais alguns testes reais de baixo valor cobrindo expiracao e falha antes do uso pleno | E11: Aberto
